pydbhub/__init__.py
pydbhub/dbhub.py
pydbhub/httphub.py
pydbhub-0.0.4.dist-info/LICENSE
pydbhub-0.0.4.dist-info/WHEEL
pydbhub-0.0.4.dist-info/METADATA
pydbhub-0.0.4.dist-info/RECORD
