Metadata-Version: 2.1
Name: pydbhub
Version: 0.0.4
Summary: pydbhub
Author-email: LeMoussel <cnhx27@gmail.com>
Classifier: License :: OSI Approved :: MIT License
